qcloudapi/__init__.py
qcloudapi/api.py
qcloudapi-0.2.dist-info/DESCRIPTION.rst
qcloudapi-0.2.dist-info/METADATA
qcloudapi-0.2.dist-info/RECORD
qcloudapi-0.2.dist-info/WHEEL
qcloudapi-0.2.dist-info/metadata.json
qcloudapi-0.2.dist-info/top_level.txt
