Metadata-Version: 2.0
Name: qcloudapi
Version: 0.2
Summary: To make a signature with the hmac algorithm. 
Home-page: https://github.com/duyixian1234/qcloudapi
Author: Yixian Du
Author-email: duyixian1233@outlook.com
License: UNKNOWN
Keywords: qcloud
Platform: UNKNOWN
Requires-Dist: hmac-signature
